mddns/__init__.py
mddns/server.py
mddns/scripts/__init__.py
mddns/scripts/server.py
mddns/test/__init__.py
mddns-0.1.4.dist-info/DESCRIPTION.rst
mddns-0.1.4.dist-info/entry_points.txt
mddns-0.1.4.dist-info/METADATA
mddns-0.1.4.dist-info/metadata.json
mddns-0.1.4.dist-info/RECORD
mddns-0.1.4.dist-info/top_level.txt
mddns-0.1.4.dist-info/WHEEL
